__init__.py
test/__init__.py
test/another_file.py
unas_api/__init__.py
unas_api/unas.py
unas_api-1.0.dist-info/licenses/LICENSE
unas_api-1.0.dist-info/METADATA
unas_api-1.0.dist-info/WHEEL
unas_api-1.0.dist-info/top_level.txt
unas_api-1.0.dist-info/RECORD
