Metadata-Version: 2.4
Name: unas-api
Version: 1.0
Summary: A simple API wrapper for the Unas API
Author-email: Attila Zsámboki <zsamboki.attila.jr@gmail.com>
Project-URL: Homepage, https://github.com/pypa/sampleproject
Project-URL: Issues, https://github.com/pypa/sampleproject/issues
Classifier: Programming Language :: Python :: 3
Classifier: License :: OSI Approved :: MIT License
Classifier: Operating System :: OS Independent
Requires-Python: >=3.8
License-File: LICENSE
Dynamic: license-file
